update_packages.py
pypi_package_updater-0.2.23.dist-info/licenses/LICENSE
pypi_updater/__init__.py
pypi_updater/_version.py
pypi_updater/formats.py
pypi_updater/parser.py
pypi_updater/pypi_client.py
pypi_updater/updater.py
tests/__init__.py
tests/test_100_percent_coverage.py
tests/test_basic.py
tests/test_branch_coverage.py
tests/test_coverage_edge_cases.py
tests/test_dead_code_analysis.py
tests/test_e2e.py
tests/test_error_handling.py
tests/test_exact_missing_lines.py
tests/test_file_updating.py
tests/test_final_coverage.py
tests/test_final_edge_cases.py
tests/test_final_seven_lines.py
tests/test_final_three_lines.py
tests/test_final_two_lines.py
tests/test_formats.py
tests/test_formats_final_coverage.py
tests/test_formats_specific_lines.py
tests/test_line_250.py
tests/test_parser_specific_lines.py
tests/test_remaining_branches.py
tests/test_specific_lines.py
tests/test_ultra_targeted_final_five.py
tests/test_updater.py
tests/test_updater_coverage.py
pypi_package_updater-0.2.23.dist-info/METADATA
pypi_package_updater-0.2.23.dist-info/WHEEL
pypi_package_updater-0.2.23.dist-info/entry_points.txt
pypi_package_updater-0.2.23.dist-info/top_level.txt
pypi_package_updater-0.2.23.dist-info/RECORD
