Metadata-Version: 2.4
Name: pypi-package-updater
Version: 0.2.23
Summary: A tool to update Python package dependencies across multiple file formats
Home-page: https://github.com/adambirds/pypi-package-updater
Author: Adam Birds
Author-email: adam.birds@adbwebdesigns.co.uk
License: MIT
Project-URL: Repository, https://github.com/adambirds/pypi-package-updater
Project-URL: Issues, https://github.com/adambirds/pypi-package-updater/issues
Classifier: Development Status :: 4 - Beta
Classifier: Intended Audience :: Developers
Classifier: License :: OSI Approved :: MIT License
Classifier: Operating System :: OS Independent
Classifier: Programming Language :: Python :: 3
Classifier: Programming Language :: Python :: 3.11
Classifier: Programming Language :: Python :: 3.12
Classifier: Programming Language :: Python :: 3.13
Classifier: Topic :: Software Development :: Libraries :: Python Modules
Classifier: Topic :: System :: Software Distribution
Requires-Python: >=3.11
License-File: LICENSE
Requires-Dist: aiohttp<4,>=3.9
Requires-Dist: packaging>=23.2
Requires-Dist: tomli>=2.0.1; python_version < "3.11"
Requires-Dist: typing-extensions>=4.11; python_version < "3.13"
Provides-Extra: dev
Requires-Dist: pytest==8.4.1; extra == "dev"
Requires-Dist: pytest-asyncio==1.1.0; extra == "dev"
Requires-Dist: pytest-mock==3.14.1; extra == "dev"
Requires-Dist: black==25.1.0; extra == "dev"
Requires-Dist: isort==6.0.1; extra == "dev"
Requires-Dist: flake8==7.3.0; extra == "dev"
Requires-Dist: mypy==1.17.1; extra == "dev"
Requires-Dist: coverage==7.10.3; extra == "dev"
Requires-Dist: pytest-cov==6.2.1; extra == "dev"
Requires-Dist: pip-tools==7.5.0; extra == "dev"
Requires-Dist: setuptools_scm==8.3.1; extra == "dev"
Dynamic: author
Dynamic: author-email
Dynamic: classifier
Dynamic: description
Dynamic: description-content-type
Dynamic: home-page
Dynamic: license
Dynamic: license-file
Dynamic: project-url
Dynamic: provides-extra
Dynamic: requires-dist
Dynamic: requires-python
Dynamic: summary
